bg.png
export.jpg
licence.md
osuplaylist/__init__.py
osuplaylist/osuplaylist.py
osuplaylist-3.1.0.dist-info/entry_points.txt
osuplaylist-3.1.0.dist-info/WHEEL
osuplaylist-3.1.0.dist-info/METADATA
osuplaylist-3.1.0.dist-info/RECORD
