Metadata-Version: 2.1
Name: osuplaylist
Version: 3.1.0
Summary: Export audio from osu to directory/to ingame collection/to steam music  or create m3u8 playlist
Home-page: https://github.com/upgradeQ/osuplaylist
License: WTFPL
Keywords: osu,steam,export,playlist,database
Author: upgradeq
Author-email: noreply@example.com
Requires-Python: >=3.6,<4.0
Classifier: Intended Audience :: End Users/Desktop
Classifier: License :: Other/Proprietary License
Classifier: Operating System :: OS Independent
Classifier: Programming Language :: Python :: 3
Classifier: Programming Language :: Python :: 3 :: Only
Classifier: Programming Language :: Python :: 3.6
Classifier: Programming Language :: Python :: 3.7
Classifier: Programming Language :: Python :: 3.8
Classifier: Topic :: Utilities
Project-URL: Documentation, https://github.com/upgradeQ/osuplaylist/blob/master/README.md
Project-URL: Repository, https://github.com/upgradeQ/osuplaylist
